pypi/__init__.py
Hasiba-0.2.dist-info/LICENSES.txt
Hasiba-0.2.dist-info/METADATA
Hasiba-0.2.dist-info/WHEEL
Hasiba-0.2.dist-info/top_level.txt
Hasiba-0.2.dist-info/RECORD
