Metadata-Version: 2.1
Name: Hasiba
Version: 0.2
Summary: This Is Simple Project
Author: Colder
Author-email: alphacoder00@gmail.com
License: UNKNOWN
Platform: UNKNOWN
Classifier: Programming Language :: Python :: 3
Classifier: License :: OSI Approved :: MIT License
Classifier: Operating System :: OS Independent
License-File: LICENSES.txt
